pandas_utils/__init__.py
pandas_utils/connection.py
pandas_utils/read.py
pandas_utils/utils.py
pandas_utils/write.py
pandas_utils_pkg-0.0.1.dist-info/LICENSE
pandas_utils_pkg-0.0.1.dist-info/METADATA
pandas_utils_pkg-0.0.1.dist-info/WHEEL
pandas_utils_pkg-0.0.1.dist-info/top_level.txt
pandas_utils_pkg-0.0.1.dist-info/RECORD
