Metadata-Version: 2.1
Name: pandas-utils-pkg
Version: 0.0.1
Summary: A helper tool for pandans and mysql
Home-page: https://github.com/SensCritique/pandas-utils-pkg
Author: Thomas Dimnet
Author-email: thomas.dimnet@gmail.com
License: UNKNOWN
Platform: UNKNOWN
Classifier: Programming Language :: Python :: 3
Classifier: License :: OSI Approved :: MIT License
Classifier: Operating System :: OS Independent
Requires-Python: >=3.8
